arm_gdb/__init__.py
arm_gdb/common.py
arm_gdb/fpu.py
arm_gdb/lib.py
arm_gdb/mpu.py
arm_gdb/nvic.py
arm_gdb/scb.py
arm_gdb/svd.py
arm_gdb/systick.py
arm_gdb-0.9.10.dist-info/LICENSE
arm_gdb-0.9.10.dist-info/METADATA
arm_gdb-0.9.10.dist-info/WHEEL
arm_gdb-0.9.10.dist-info/top_level.txt
arm_gdb-0.9.10.dist-info/RECORD
