Metadata-Version: 2.1
Name: arm-gdb
Version: 0.9.10
Summary: Python module for GDB to analyze ARM core registers
Author-email: Max Sikström <max@pengi.se>
License: Copyright (c) 2023 Max Sikström
Project-URL: Homepage, https://github.com/pengi/arm_gdb
Classifier: Development Status :: 4 - Beta
Classifier: Intended Audience :: Developers
Classifier: Natural Language :: English
Classifier: License :: OSI Approved :: MIT License
Classifier: Programming Language :: Python
Classifier: Programming Language :: Python :: 3
Requires-Python: >=3.6
License-File: LICENSE
Requires-Dist: cmsis-svd >=0.4
